inte_sites/__init__.py
inte_sites/apps.py
inte_sites/models.py
inte_sites/sites.py
inte_sites/tests/__init__.py
inte_sites/tests/test_sites.py
inte_sites/tests/urls.py
inte_sites-0.1.1.dist-info/AUTHORS
inte_sites-0.1.1.dist-info/LICENSE
inte_sites-0.1.1.dist-info/METADATA
inte_sites-0.1.1.dist-info/WHEEL
inte_sites-0.1.1.dist-info/top_level.txt
inte_sites-0.1.1.dist-info/RECORD
